adaptive_router/__init__.py
adaptive_router/core/__init__.py
adaptive_router/core/cluster_engine.py
adaptive_router/core/provider_registry.py
adaptive_router/core/router.py
adaptive_router/core/trainer.py
adaptive_router/dataset/__init__.py
adaptive_router/evaluators/__init__.py
adaptive_router/exceptions/__init__.py
adaptive_router/exceptions/core.py
adaptive_router/models/api.py
adaptive_router/models/config.py
adaptive_router/models/health.py
adaptive_router/models/routing.py
adaptive_router/models/storage.py
adaptive_router/models/train.py
adaptive_router/py.typed
adaptive_router-0.1.8.dist-info/WHEEL
adaptive_router-0.1.8.dist-info/METADATA
adaptive_router-0.1.8.dist-info/RECORD
