Metadata-Version: 2.4
Name: adaptive_router
Version: 0.1.8
Summary: Intelligent LLM Infrastructure with Smart Model Selection
Keywords: llm,ai,model-selection,machine-learning,adaptive
Author: Botir Khaltaev
Author-email: Botir Khaltaev <botirkhaltaev@llmadaptive.uk>
License-Expression: MIT
Classifier: Development Status :: 3 - Alpha
Classifier: Intended Audience :: Developers
Classifier: License :: OSI Approved :: MIT License
Classifier: Operating System :: OS Independent
Classifier: Programming Language :: Python :: 3
Classifier: Programming Language :: Python :: 3.11
Classifier: Programming Language :: Python :: 3.12
Classifier: Topic :: Scientific/Engineering :: Artificial Intelligence
Classifier: Topic :: Software Development :: Libraries :: Python Modules
Classifier: Typing :: Typed
Requires-Dist: pydantic>=2.11.5,<3
Requires-Dist: sentence-transformers>=5.2.0,<6
Requires-Dist: datasets>=4.4.1
Requires-Dist: polars>=1.35.2
Requires-Dist: deepeval>=3.7.0
Requires-Dist: einops>=0.8.1
Requires-Dist: adaptive-router-core>=0.1.11,<1 ; extra == 'cpu'
Requires-Dist: torch>=2.5.1 ; extra == 'cpu'
Requires-Dist: adaptive-router-core-cu12>=0.1.11,<1 ; sys_platform == 'linux' and extra == 'cu12'
Requires-Dist: torch>=2.5.1 ; extra == 'cu12'
Requires-Python: >=3.11, <4.0
Project-URL: Bug Tracker, https://github.com/Egham-7/adaptive/issues
Project-URL: Documentation, https://docs.llmadaptive.uk
Project-URL: Homepage, https://llmadaptive.uk
Project-URL: Repository, https://github.com/Egham-7/adaptive
Provides-Extra: cpu
Provides-Extra: cu12
